pyduro/__init__.py
pyduro/__main__.py
pyduro/actions/__init__.py
pyduro/actions/discover.py
pyduro/actions/get.py
pyduro/actions/set.py
pyduro/protocol/__init__.py
pyduro/protocol/frame.py
pyduro-1.1.0.dist-info/LICENSE
pyduro-1.1.0.dist-info/METADATA
pyduro-1.1.0.dist-info/WHEEL
pyduro-1.1.0.dist-info/top_level.txt
pyduro-1.1.0.dist-info/RECORD
