Metadata-Version: 2.1
Name: pyduro
Version: 1.1.0
Summary: A Pypi library to communicate with Aduro (H1) wood/pellet burner via NBE communication
Home-page: https://github.com/clementprevot/pyduro
Author: Clément PRÉVOT
Author-email: clementprevot+pypi@gmail.com
License: MIT
Keywords: aduro h1 wood pellet burner nbe
Platform: UNKNOWN
Classifier: License :: OSI Approved :: MIT License
Classifier: Operating System :: OS Independent
Classifier: Programming Language :: Python :: 3
Classifier: Programming Language :: Python :: 3.6
Classifier: Intended Audience :: Developers
Classifier: Topic :: Software Development :: Libraries
Classifier: Topic :: Home Automation
Classifier: Natural Language :: English
Classifier: Natural Language :: French
Classifier: Development Status :: 4 - Beta
Requires-Python: >=3.6
